[
  {
    "id": 1,
    "firmano": null,
    "yetkiid": 2,
    "bolumid": 6,
    "havuz": null,
    "deguser": null,
    "degtarsaat": null,
    "olususer": null,
    "olustarsaat": null,
    "Modul": ""
  },
  {
    "id": 2,
    "firmano": null,
    "yetkiid": 2,
    "bolumid": 8,
    "havuz": null,
    "deguser": null,
    "degtarsaat": null,
    "olususer": null,
    "olustarsaat": null,
    "Modul": ""
  },
  {
    "id": 3,
    "firmano": null,
    "yetkiid": 2,
    "bolumid": 15,
    "havuz": null,
    "deguser": null,
    "degtarsaat": null,
    "olususer": null,
    "olustarsaat": null,
    "Modul": ""
  },
  {
    "id": 4,
    "firmano": null,
    "yetkiid": 2,
    "bolumid": 16,
    "havuz": null,
    "deguser": null,
    "degtarsaat": null,
    "olususer": null,
    "olustarsaat": null,
    "Modul": ""
  }
]