{
  "dbo.ana_menu_hrk": {
    "kolonlar": [
      "id",
      "user_kod",
      "name",
      "class",
      "icon_index",
      "cap_tr",
      "Modul"
    ],
    "veriler": [
      {
        "id": 1,
        "user_kod": "MARKET",
        "name": "mn_pomvardiya",
        "class": "TdxBarLargeButton",
        "icon_index": 0,
        "cap_tr": "P.Vardiya Hesabı",
        "Modul": null
      },
      {
        "id": 2,
        "user_kod": "MARKET",
        "name": "mn_marvardi",
        "class": "TdxBarLargeButton",
        "icon_index": 2,
        "cap_tr": "M. Vardiya Hesabı",
        "Modul": null
      },
      {
        "id": 3,
        "user_kod": "MARKET",
        "name": "mn_marsatiade",
        "class": "TdxBarLargeButton",
        "icon_index": 3,
        "cap_tr": "M.Satış / İade İşlemi",
        "Modul": null
      },
      {
        "id": 4,
        "user_kod": "MARKET",
        "name": "mn_carikart",
        "class": "TdxBarLargeButton",
        "icon_index": 7,
        "cap_tr": "Cari Hesap Kartları",
        "Modul": null
      },
      {
        "id": 5,
        "user_kod": "MARKET",
        "name": "mn_hizliislm",
        "class": "TdxBarLargeButton",
        "icon_index": 10,
        "cap_tr": "Hızlı İşlem",
        "Modul": null
      },
      {
        "id": 6,
        "user_kod": "MARKET",
        "name": "mn_kasaislm",
        "class": "TdxBarLargeButton",
        "icon_index": 13,
        "cap_tr": "Kasa İşlemleri",
        "Modul": null
      },
      {
        "id": 7,
        "user_kod": "MARKET",
        "name": "mn_bankakart",
        "class": "TdxBarLargeButton",
        "icon_index": 6,
        "cap_tr": "Banka Hesap Kartları",
        "Modul": null
      },
      {
        "id": 8,
        "user_kod": "MARKET",
        "name": "mn_marstkkart",
        "class": "TdxBarLargeButton",
        "icon_index": 4,
        "cap_tr": "Market Stok Kartları",
        "Modul": null
      },
      {
        "id": 9,
        "user_kod": "MARKET",
        "name": "mn_fatliste",
        "class": "TdxBarLargeButton",
        "icon_index": 8,
        "cap_tr": "Fatura Listesi",
        "Modul": null
      },
      {
        "id": 10,
        "user_kod": "MARKET",
        "name": "mn_rapkarzarar",
        "class": "TdxBarLargeButton",
        "icon_index": 12,
        "cap_tr": "Kar - Zarar Raporu",
        "Modul": null
      },
      {
        "id": 11,
        "user_kod": "YÖNETİM",
        "name": "mn_pomvardiya",
        "class": "TdxBarLargeButton",
        "icon_index": 0,
        "cap_tr": "P.Vardiya Hesabı",
        "Modul": null
      },
      {
        "id": 12,
        "user_kod": "YÖNETİM",
        "name": "mn_marvardi",
        "class": "TdxBarLargeButton",
        "icon_index": 2,
        "cap_tr": "M. Vardiya Hesabı",
        "Modul": null
      },
      {
        "id": 13,
        "user_kod": "YÖNETİM",
        "name": "mn_marsatiade",
        "class": "TdxBarLargeButton",
        "icon_index": 3,
        "cap_tr": "M.Satış / İade İşlemi",
        "Modul": null
      },
      {
        "id": 14,
        "user_kod": "YÖNETİM",
        "name": "mn_carikart",
        "class": "TdxBarLargeButton",
        "icon_index": 7,
        "cap_tr": "Cari Hesap Kartları",
        "Modul": null
      },
      {
        "id": 15,
        "user_kod": "YÖNETİM",
        "name": "mn_hizliislm",
        "class": "TdxBarLargeButton",
        "icon_index": 10,
        "cap_tr": "Hızlı İşlem",
        "Modul": null
      },
      {
        "id": 16,
        "user_kod": "YÖNETİM",
        "name": "mn_kasaislm",
        "class": "TdxBarLargeButton",
        "icon_index": 13,
        "cap_tr": "Kasa İşlemleri",
        "Modul": null
      },
      {
        "id": 17,
        "user_kod": "YÖNETİM",
        "name": "mn_bankakart",
        "class": "TdxBarLargeButton",
        "icon_index": 6,
        "cap_tr": "Banka Hesap Kartları",
        "Modul": null
      },
      {
        "id": 18,
        "user_kod": "YÖNETİM",
        "name": "mn_marstkkart",
        "class": "TdxBarLargeButton",
        "icon_index": 4,
        "cap_tr": "Market Stok Kartları",
        "Modul": null
      },
      {
        "id": 19,
        "user_kod": "YÖNETİM",
        "name": "mn_fatliste",
        "class": "TdxBarLargeButton",
        "icon_index": 8,
        "cap_tr": "Fatura Listesi",
        "Modul": null
      },
      {
        "id": 20,
        "user_kod": "YÖNETİM",
        "name": "mn_rapkarzarar",
        "class": "TdxBarLargeButton",
        "icon_index": 12,
        "cap_tr": "Kar - Zarar Raporu",
        "Modul": null
      }
    ]
  },
  "dbo.ana_menu_mas": {
    "kolonlar": [
      "id",
      "user_kod",
      "kisayol_cap",
      "style",
      "coklu_satir",
      "Modul",
      "Eski_Style"
    ],
    "veriler": [
      {
        "id": 1,
        "user_kod": "MARKET",
        "kisayol_cap": true,
        "style": 4,
        "coklu_satir": false,
        "Modul": null,
        "Eski_Style": true
      },
      {
        "id": 2,
        "user_kod": "YÖNETİM",
        "kisayol_cap": true,
        "style": 4,
        "coklu_satir": false,
        "Modul": null,
        "Eski_Style": true
      }
    ]
  },
  "dbo.userformgrup": {
    "kolonlar": [
      "id",
      "firmano",
      "kod",
      "deguser",
      "degtarsaat",
      "olususer",
      "olustarsaat"
    ],
    "veriler": []
  },
  "dbo.userformhak": {
    "kolonlar": [
      "id",
      "firmano",
      "userkod",
      "formkod",
      "h1",
      "h2",
      "h3",
      "h4",
      "h5",
      "h6",
      "h7",
      "h8",
      "h9",
      "h10",
      "h11",
      "h12",
      "h13",
      "h14",
      "h15",
      "h16",
      "h17",
      "h18",
      "h19",
      "h20",
      "deguser",
      "degtarsaat",
      "olususer",
      "olustarsaat"
    ],
    "veriler": []
  },
  "dbo.userformhrk": {
    "kolonlar": [
      "id",
      "formid",
      "firmano",
      "tan1",
      "tan2",
      "tan3",
      "tan4",
      "tan5",
      "tan6",
      "deguser",
      "degtarsaat",
      "olususer",
      "olustarsaat"
    ],
    "veriler": []
  },
  "dbo.userformlar": {
    "kolonlar": [
      "id",
      "firmano",
      "grupkod",
      "formkod",
      "fromack",
      "sira",
      "deguser",
      "degtarsaat",
      "olususer",
      "olustarsaat"
    ],
    "veriler": []
  }
}